gstor_adapter/__init__.py
gstor_adapter/client.py
gstore_adapter/__init__.py
gstore_adapter/client.py
gstore_adapter/templates/fgdc_template.xml
gstore_adapter/templates/watershed_template.json
vw_gstore_adapter-1.0.0.dist-info/DESCRIPTION.rst
vw_gstore_adapter-1.0.0.dist-info/METADATA
vw_gstore_adapter-1.0.0.dist-info/metadata.json
vw_gstore_adapter-1.0.0.dist-info/RECORD
vw_gstore_adapter-1.0.0.dist-info/top_level.txt
vw_gstore_adapter-1.0.0.dist-info/WHEEL
