Metadata-Version: 2.0
Name: vw-gstore-adapter
Version: 1.0.0
Summary: Client for the UNM GSToRE REST Geospatial Data Service
Home-page: https://virtualwatershed.org/docs
Author: UNKNOWN
Author-email: maturner01@gmail.com
License: UNKNOWN
Keywords: REST,Hydrology,Datastore as a Service
Platform: UNKNOWN
Requires-Dist: configparser (>=3.3)
Requires-Dist: Jinja2 (>=2.8)
Requires-Dist: MarkupSafe (>=0.23)
Requires-Dist: nose (>=1.3.7)
Requires-Dist: requests (>=2.9.1)
Requires-Dist: python-swiftclient (>=3.0.0)
